tests/__init__.py
tests/test_cal.py
workday_duration/__init__.py
workday_duration/utils.py
workday_duration-1.0.8.dist-info/METADATA
workday_duration-1.0.8.dist-info/WHEEL
workday_duration-1.0.8.dist-info/top_level.txt
workday_duration-1.0.8.dist-info/RECORD
