Metadata-Version: 2.1
Name: workday-duration
Version: 1.0.8
Summary: calculator duration days from one time to another
Home-page: https://github.com/hanxianfeng123/workday-duration
Author: hanxianfeng123
Author-email: hanxianfeng123@foxmail.com
License: MIT
Requires-Python: >=3.6
Requires-Dist: chinesecalendar
